wirelesstagpy/__init__.py
wirelesstagpy/binaryevent.py
wirelesstagpy/constants.py
wirelesstagpy/exceptions.py
wirelesstagpy/notificationconfig.py
wirelesstagpy/sensor.py
wirelesstagpy/sensortag.py
wirelesstagpy/utils.py
wirelesstagpy-0.8.1.dist-info/LICENSE
wirelesstagpy-0.8.1.dist-info/METADATA
wirelesstagpy-0.8.1.dist-info/WHEEL
wirelesstagpy-0.8.1.dist-info/top_level.txt
wirelesstagpy-0.8.1.dist-info/RECORD
