Metadata-Version: 2.1
Name: wirelesstagpy
Version: 0.8.1
Summary: Simple python wrapper over wirelesstags REST API
Home-page: https://github.com/sergeymaysak/wirelesstagpy/
Author: Sergiy Maysak
Author-email: sergey.maysak@gmail.com
License: MIT
Platform: any
Classifier: Programming Language :: Python :: 3.5
Classifier: Programming Language :: Python :: 3.6
Classifier: Programming Language :: Python :: 3.7
Classifier: Programming Language :: Python :: 3.8
Classifier: Programming Language :: Python :: 3.9
Classifier: Development Status :: 4 - Beta
Classifier: Natural Language :: English
Classifier: Intended Audience :: Developers
Classifier: License :: OSI Approved :: MIT License
Classifier: Operating System :: OS Independent
Classifier: Topic :: Home Automation
Requires-Python: >=3
Provides-Extra: testing
License-File: LICENSE
